textual_games/__init__.py
textual_games/css.tcss
textual_games/enums.py
textual_games/game.py
textual_games/games/connectfour.py
textual_games/games/tictactoe.py
textual_games/grid.py
textual_games/manager.py
textual_games/menu.py
textual_games/simplebutton.py
textual_games/source_decorator.py
textual_games/spinner.py
textual_games-0.2.0.dist-info/METADATA
textual_games-0.2.0.dist-info/WHEEL
textual_games-0.2.0.dist-info/entry_points.txt
textual_games-0.2.0.dist-info/RECORD
